forked_graphene_sqlalchemy-2.1.0.dist-info/METADATA
forked_graphene_sqlalchemy-2.1.0.dist-info/RECORD
forked_graphene_sqlalchemy-2.1.0.dist-info/WHEEL
forked_graphene_sqlalchemy-2.1.0.dist-info/top_level.txt
graphene_sqlalchemy/__init__.py
graphene_sqlalchemy/converter.py
graphene_sqlalchemy/fields.py
graphene_sqlalchemy/registry.py
graphene_sqlalchemy/types.py
graphene_sqlalchemy/utils.py
graphene_sqlalchemy/tests/__init__.py
graphene_sqlalchemy/tests/models.py
graphene_sqlalchemy/tests/test_connectionfactory.py
graphene_sqlalchemy/tests/test_converter.py
graphene_sqlalchemy/tests/test_query.py
graphene_sqlalchemy/tests/test_reflected.py
graphene_sqlalchemy/tests/test_registry.py
graphene_sqlalchemy/tests/test_schema.py
graphene_sqlalchemy/tests/test_types.py
graphene_sqlalchemy/tests/test_utils.py
